stac_fastapi/static/__about__.py
stac_fastapi/static/__init__.py
stac_fastapi/static/app.py
stac_fastapi/static/api/__init__.py
stac_fastapi/static/api/api.py
stac_fastapi/static/api/config.py
stac_fastapi/static/api/core_client.py
stac_fastapi/static/api/filters_client.py
stac_fastapi/static/api/links.py
stac_fastapi/static/api/middlewares.py
stac_fastapi/static/api/models.py
stac_fastapi/static/core/__init__.py
stac_fastapi/static/core/client.py
stac_fastapi/static/core/errors.py
stac_fastapi/static/core/fetch.py
stac_fastapi/static/core/filter_cql2.py
stac_fastapi/static/core/filter_depth.py
stac_fastapi/static/core/filter_page.py
stac_fastapi/static/core/filter_spatial_extent.py
stac_fastapi/static/core/filter_temporal_extent.py
stac_fastapi/static/core/pagination.py
stac_fastapi/static/core/walk.py
stac_fastapi/static/core/walk_collections.py
stac_fastapi/static/core/walk_filter.py
stac_fastapi/static/core/walk_items.py
stac_fastapi/static/core/walk_path.py
stac_fastapi/static/core/walk_result.py
stac_fastapi/static/core/compat/__init__.py
stac_fastapi/static/core/compat/fromisoformat.py
stac_fastapi/static/core/lib/__init__.py
stac_fastapi/static/core/lib/datetimes_intersect.py
stac_fastapi/static/core/lib/geometries_intersect.py
stac_fastapi/static/core/lib/tiered_cache.py
stac_fastapi/static/core/model/__init__.py
stac_fastapi/static/core/model/cql2.py
stac_fastapi/static/core/model/layout.py
stac_fastapi/static/core/model/links.py
stac_fastapi/static/core/model/spatial.py
stac_fastapi/static/core/model/temporal.py
stac_fastapi/static/core/requests/__init__.py
stac_fastapi/static/core/requests/file_href.py
stac_fastapi/static/core/requests/file_session.py
stac_fastapi_static-1.0.1.dist-info/licenses/LICENCE.txt
stac_fastapi_static-1.0.1.dist-info/METADATA
stac_fastapi_static-1.0.1.dist-info/WHEEL
stac_fastapi_static-1.0.1.dist-info/entry_points.txt
stac_fastapi_static-1.0.1.dist-info/top_level.txt
stac_fastapi_static-1.0.1.dist-info/RECORD
