Metadata-Version: 2.4
Name: stac-fastapi.static
Version: 1.0.1
Summary: An implementation of STAC API based on the FastAPI framework using a static catalog as backend.
Author-email: Pierre Fontbonne <pierre.fontbonne@uca.fr>
Maintainer-email: Pierre Fontbonne <pierre.fontbonne@uca.fr>, Yannick Guéhenneux <yannick.guehenneux@uca.fr>
License-Expression: etalab-2.0
Project-URL: Homepage, https://github.com/fntb/stac-fastapi-static
Project-URL: Documentation, https://github.com/fntb/stac-fastapi-static
Project-URL: Repository, https://github.com/fntb/stac-fastapi-static
Project-URL: Issues, https://github.com/fntb/stac-fastapi-static
Keywords: STAC,FastAPI,stac-fastapi,static,fs,filesystem
Classifier: Intended Audience :: Developers
Classifier: Intended Audience :: Information Technology
Classifier: Intended Audience :: Science/Research
Classifier: Programming Language :: Python :: 3.10
Classifier: Programming Language :: Python :: 3.11
Classifier: Programming Language :: Python :: 3.12
Classifier: Development Status :: 4 - Beta
Requires-Python: >=3.10
License-File: LICENCE.txt
Requires-Dist: requests<3,>=2.32
Requires-Dist: requests-cache<2,>=1.2
Requires-Dist: requests_file<3,>=2.1
Requires-Dist: xxhash<4,>=3.5
Requires-Dist: pydantic<3,>=2.10
Requires-Dist: stac_pydantic<4,>=3.1
Requires-Dist: stac-fastapi.api<6,>=5.1
Requires-Dist: stac-fastapi.extensions<6,>=5.1
Requires-Dist: stac-fastapi.types<6,>=5.1
Requires-Dist: brotli_asgi<2,>=1.4
Requires-Dist: shapely<3,>=2.0
Requires-Dist: orjson<4,>=3.10
Requires-Dist: cql2<1,>=0.3
Requires-Dist: uvicorn[standard]
Dynamic: license-file
